chinus/__init__.py
chinus/decorator/__init__.py
chinus/decorator/warning/__init__.py
chinus/decorator/warning/not_used_return_value.py
chinus/test/__init__.py
chinus/test/test.py
chinus/tools/__init__.py
chinus/tools/json.py
chinus/tools/git/__init__.py
chinus/tools/git/status.py
chinus/tools/paths/__init__.py
chinus/tools/paths/get/__init__.py
chinus/tools/paths/get/absolute_path.py
chinus/tools/paths/get/project_root.py
chinus/tools/print_input_utils/__init__.py
chinus/tools/print_input_utils/multi_line_io.py
chinus-0.3.5.dist-info/METADATA
chinus-0.3.5.dist-info/WHEEL
chinus-0.3.5.dist-info/top_level.txt
chinus-0.3.5.dist-info/RECORD
